exifdategeobatch/__init__.py
exifdategeobatch/main.py
exifdategeobatch/custom_widgets/__init__.py
exifdategeobatch/custom_widgets/custom_list_view.py
exifdategeobatch/ui_elements/__init__.py
exifdategeobatch/ui_elements/exif_display_manager.py
exifdategeobatch/ui_elements/image_config_app.py
exifdategeobatch/utils/__init__.py
exifdategeobatch/utils/exif_utils.py
exifdategeobatch/utils/image_loader_thread.py
exifdategeobatch/utils/python_bridge.py
ExifDateGeoBatch-0.1.0.dist-info/LICENSE
ExifDateGeoBatch-0.1.0.dist-info/METADATA
ExifDateGeoBatch-0.1.0.dist-info/WHEEL
ExifDateGeoBatch-0.1.0.dist-info/entry_points.txt
ExifDateGeoBatch-0.1.0.dist-info/top_level.txt
ExifDateGeoBatch-0.1.0.dist-info/RECORD
