Metadata-Version: 2.1
Name: ExifDateGeoBatch
Version: 0.1.0
Summary: Efficiently manage and update photo EXIF data with ease. Built with PyQt6 and Piexif, this tool offers intuitive batch editing of the dates and coordinates of an image.
Author-email: Dan Plamadeala <cornul11@gmail.com>
License: GPL-3.0-or-later
Classifier: Development Status :: 3 - Alpha
Classifier: Intended Audience :: End Users/Desktop
Classifier: License :: OSI Approved :: GNU General Public License v3 or later (GPLv3+)
Classifier: Operating System :: OS Independent
Classifier: Programming Language :: Python :: 3
Classifier: Programming Language :: Python :: 3.6
Classifier: Programming Language :: Python :: 3.7
Classifier: Programming Language :: Python :: 3.8
Classifier: Programming Language :: Python :: 3.9
Classifier: Programming Language :: Python :: 3.10
Classifier: Programming Language :: Python :: 3.11
Classifier: Programming Language :: Python :: 3.12
Classifier: Topic :: Multimedia :: Graphics :: Editors
Classifier: Topic :: Multimedia :: Graphics
Requires-Python: >=3.6
License-File: LICENSE
Requires-Dist: piexif ==1.1.3
Requires-Dist: PyQt6 ==6.6.1
Requires-Dist: PyQt6-Qt6 ==6.6.1
Requires-Dist: PyQt6-sip ==13.6.0
Requires-Dist: PyQt6-WebEngine ==6.6.0
Requires-Dist: PyQt6-WebEngine-Qt6 ==6.6.1
